Metadata-Version: 2.4
Name: s2shores
Version: 1.0.2
Summary: A python library for estimating coastal bathymetry
Author: Rafael Almar, Stephanie Artigues, Erwin Bergsma, Romain Degoul, Alain Giros, Adrien Klotz, Yannick Lasne, Solange Lemai-Chenevier, Alexia Mondot, Gregoire Thoumyre, Pierre Tysebaert
License: Apache-2.0
Project-URL: Homepage, https://github.com/CNES/S2Shores
Requires-Python: >=3.12
License-File: LICENSE.txt
License-File: AUTHORS.rst
Requires-Dist: click
Requires-Dist: PyYAML
Requires-Dist: dask[dataframe]
Requires-Dist: dask[distributed]
Requires-Dist: jupyter-server-proxy
Requires-Dist: sphinx-rtd-theme
Requires-Dist: pyarrow
Requires-Dist: numpy<2.0
Requires-Dist: scipy
Requires-Dist: myst-nb
Requires-Dist: scikit-image
Requires-Dist: xarray
Requires-Dist: netcdf4
Requires-Dist: pandas
Requires-Dist: pytest
Requires-Dist: pytest-cov
Requires-Dist: pytest-xdist
Requires-Dist: matplotlib
Requires-Dist: Sphinx>=4.2
Requires-Dist: setuptools
Requires-Dist: Shapely>=1.6
Requires-Dist: cmcrameri
Requires-Dist: pydantic
Dynamic: license-file
